shirao_testpip_1/shirao_testpip_1.py
shirao_testpip_1-0.1.dist-info/METADATA
shirao_testpip_1-0.1.dist-info/WHEEL
shirao_testpip_1-0.1.dist-info/top_level.txt
shirao_testpip_1-0.1.dist-info/RECORD
