Metadata-Version: 2.1
Name: shirao-testpip-1
Version: 0.1
Summary: A simple library to double the input
Home-page: https://github.com/yourusername/mylibrary
Author: Your Name
Author-email: your.email@example.com
